nonebot_plugin_kurogames/Static/Exploration.html
nonebot_plugin_kurogames/Static/MCResult.html
nonebot_plugin_kurogames/Static/Outputs/exploration_template.html
nonebot_plugin_kurogames/Static/Outputs/mc_rendered_template.html
nonebot_plugin_kurogames/Static/Outputs/mc_role_detail_template.html
nonebot_plugin_kurogames/Static/Outputs/mc_slash_detail_template.html
nonebot_plugin_kurogames/Static/Outputs/mc_tower_detail_template.html
nonebot_plugin_kurogames/Static/Outputs/rendered_template.html
nonebot_plugin_kurogames/Static/PNSResult.html
nonebot_plugin_kurogames/Static/PNSRoleDetail.html
nonebot_plugin_kurogames/Static/Pics/help_pics/HELP_PIC.png
nonebot_plugin_kurogames/Static/Pics/mc_pics/4star_bg.png
nonebot_plugin_kurogames/Static/Pics/mc_pics/5star_bg.png
nonebot_plugin_kurogames/Static/Pics/mc_pics/active-icon.png
nonebot_plugin_kurogames/Static/Pics/mc_pics/bg-mask.png
nonebot_plugin_kurogames/Static/Pics/mc_pics/breach.png
nonebot_plugin_kurogames/Static/Pics/mc_pics/calabash.png
nonebot_plugin_kurogames/Static/Pics/mc_pics/energy-icon.png
nonebot_plugin_kurogames/Static/Pics/mc_pics/explore_bg.png
nonebot_plugin_kurogames/Static/Pics/mc_pics/header_bg.jpg
nonebot_plugin_kurogames/Static/Pics/mc_pics/logo.png
nonebot_plugin_kurogames/Static/Pics/mc_pics/mc.png
nonebot_plugin_kurogames/Static/Pics/mc_pics/mc_elements/冷凝.png
nonebot_plugin_kurogames/Static/Pics/mc_pics/mc_elements/导电.png
nonebot_plugin_kurogames/Static/Pics/mc_pics/mc_elements/气动.png
nonebot_plugin_kurogames/Static/Pics/mc_pics/mc_elements/湮灭.png
nonebot_plugin_kurogames/Static/Pics/mc_pics/mc_elements/热熔.png
nonebot_plugin_kurogames/Static/Pics/mc_pics/mc_elements/衍射.png
nonebot_plugin_kurogames/Static/Pics/mc_pics/myDataBG.png
nonebot_plugin_kurogames/Static/Pics/mc_pics/no-role.png
nonebot_plugin_kurogames/Static/Pics/mc_pics/role_detail_bg.png
nonebot_plugin_kurogames/Static/Pics/mc_pics/skill-bg.png
nonebot_plugin_kurogames/Static/Pics/mc_pics/slash_A.png
nonebot_plugin_kurogames-0.2.29.dist-info/METADATA
nonebot_plugin_kurogames-0.2.29.dist-info/WHEEL
nonebot_plugin_kurogames-0.2.29.dist-info/licenses/LICENSE
nonebot_plugin_kurogames-0.2.29.dist-info/RECORD
