Metadata-Version: 2.4
Name: nonebot-plugin-kurogames
Version: 0.2.29
Summary: 库洛游戏数据详情 谢比螺六~
License: MIT
License-File: LICENSE
Author: ConcyWee
Author-email: concywee@163.com
Requires-Python: >=3.8
Classifier: License :: OSI Approved :: MIT License
Classifier: Programming Language :: Python :: 3
Classifier: Programming Language :: Python :: 3.8
Classifier: Programming Language :: Python :: 3.9
Classifier: Programming Language :: Python :: 3.10
Classifier: Programming Language :: Python :: 3.11
Classifier: Programming Language :: Python :: 3.12
Classifier: Programming Language :: Python :: 3.13
Classifier: Programming Language :: Python :: 3.14
Requires-Dist: httpx (>=0.27.0)
Requires-Dist: jinja2 (>=3.0.0)
Requires-Dist: nonebot-adapter-onebot (>=2.2.3)
Requires-Dist: nonebot-plugin-apscheduler (>=0.5.0)
Requires-Dist: nonebot2 (>=2.2.1)
Requires-Dist: playwright (>=1.30.0)
Requires-Dist: pycryptodome (>=3.21.0)
Project-URL: Homepage, https://github.com/ConcyWee/nonebot-plugin-kurogames
Project-URL: Repository, https://github.com/ConcyWee/nonebot-plugin-kurogames
